cpylog/__init__.py
cpylog/colorama_utils.py
cpylog/html_utils.py
cpylog/jupyter_utils.py
cpylog/screen_utils.py
cpylog/test_log.py
cpylog/utils.py
cpylog/warning_redirector.py
cpylog-1.6.0.dist-info/licenses/LICENSE.txt
cpylog-1.6.0.dist-info/METADATA
cpylog-1.6.0.dist-info/WHEEL
cpylog-1.6.0.dist-info/top_level.txt
cpylog-1.6.0.dist-info/RECORD
