Metadata-Version: 2.4
Name: cpylog
Version: 1.6.0
Summary: A simple pure python colorama/HTML capable logger
Author: Steve Doyle
Project-URL: homepage, https://github.com/SteveDoyle2/cpylog/
Project-URL: issue_tracker, https://github.com/SteveDoyle2/cpylog/issues
Project-URL: documentation, https://github.com/SteveDoyle2/cpylog/
Project-URL: repository, https://github.com/SteveDoyle2/cpylog.git
Classifier: Topic :: Software Development
Classifier: Intended Audience :: Developers
Classifier: Operating System :: OS Independent
Classifier: Programming Language :: Python
Classifier: Programming Language :: Python :: 3
Classifier: Programming Language :: Python :: 3.10
Classifier: Programming Language :: Python :: 3.11
Classifier: Programming Language :: Python :: 3.12
Classifier: Programming Language :: Python :: 3.13
Classifier: Topic :: Software Development :: Libraries :: Python Modules
Requires-Python: >=3.10
License-File: LICENSE.txt
Dynamic: license-file
